lektor_shortcodes/__init__.py
lektor_shortcodes/scodes.py
lektor_shortcodes-0.2.7.dist-info/METADATA
lektor_shortcodes-0.2.7.dist-info/WHEEL
lektor_shortcodes-0.2.7.dist-info/entry_points.txt
lektor_shortcodes-0.2.7.dist-info/top_level.txt
lektor_shortcodes-0.2.7.dist-info/RECORD
