Metadata-Version: 2.1
Name: lektor-shortcodes
Version: 0.2.7
Summary: The Lektor Shortcodes plugin allows you to use shortcodes (shortcodes are something like custom tags) in your fields (not templates), so your content doesn't have to have repetitive snippets over and over.
Home-page: https://github.com/skorokithakis/lektor-shortcodes
Author: Stavros Korokithakis,,,
Author-email: hi@stavros.io
License: MIT
Keywords: lektor shortcodes
Platform: UNKNOWN
